greenlet/__init__.py
greenstack_greenlet-1.0.2.dist-info/DESCRIPTION.rst
greenstack_greenlet-1.0.2.dist-info/METADATA
greenstack_greenlet-1.0.2.dist-info/RECORD
greenstack_greenlet-1.0.2.dist-info/WHEEL
greenstack_greenlet-1.0.2.dist-info/metadata.json
greenstack_greenlet-1.0.2.dist-info/top_level.txt
